aioerl/__init__.py
aioerl/main.py
aioerl/tests/__init__.py
aioerl/tests/test_aioerl.py
aioerl/utils.py
aioerl-0.0.20200813.dist-info/LICENSE
aioerl-0.0.20200813.dist-info/WHEEL
aioerl-0.0.20200813.dist-info/METADATA
aioerl-0.0.20200813.dist-info/RECORD
