Metadata-Version: 2.1
Name: aioerl
Version: 0.0.20200813
Summary: a python library that mimics the philosophy of Erlang's processes with asyncio tasks
License: GPL-3.0-only
Author: Jordi Masip
Author-email: jordi@masip.cat
Requires-Python: >=3.7,<4.0
Classifier: Development Status :: 3 - Alpha
Classifier: Framework :: AsyncIO
Classifier: License :: OSI Approved :: GNU General Public License v3 (GPLv3)
Classifier: Programming Language :: Python :: 3
Classifier: Programming Language :: Python :: 3.7
Classifier: Programming Language :: Python :: 3.8
